tree_sitter_ada/__init__.py
tree_sitter_ada/__init__.pyi
tree_sitter_ada/_binding.abi3.so
tree_sitter_ada/binding.c
tree_sitter_ada/py.typed
tree_sitter_ada/queries/folds.scm
tree_sitter_ada/queries/highlights.scm
tree_sitter_ada/queries/locals.scm
tree_sitter_ada/queries/textobjects.scm
tree_sitter_ada-0.1.0.dist-info/METADATA
tree_sitter_ada-0.1.0.dist-info/WHEEL
tree_sitter_ada-0.1.0.dist-info/top_level.txt
tree_sitter_ada-0.1.0.dist-info/RECORD
tree_sitter_ada-0.1.0.dist-info/licenses/LICENSE.txt
