Metadata-Version: 2.4
Name: tree-sitter-ada
Version: 0.1.0
Summary: Ada grammar for tree-sitter
Author: Emmanuel Briot
License: MIT License
Project-URL: Homepage, https://github.com/briot/tree-sitter-ada
Keywords: incremental,parsing,tree-sitter,ada
Classifier: Intended Audience :: Developers
Classifier: Topic :: Software Development :: Compilers
Classifier: Topic :: Text Processing :: Linguistic
Classifier: Typing :: Typed
Requires-Python: >=3.10
License-File: LICENSE.txt
Requires-Dist: build>=1.3.0
Requires-Dist: twine>=6.2.0
Provides-Extra: core
Requires-Dist: tree-sitter~=0.24; extra == "core"
Dynamic: license-file
